PyISE/PyISE.py
PyISE/__init__.py
pyise/__init__.py
pyise/pyise.py
pyise-0.0.3.dist-info/LICENSE
pyise-0.0.3.dist-info/METADATA
pyise-0.0.3.dist-info/WHEEL
pyise-0.0.3.dist-info/top_level.txt
pyise-0.0.3.dist-info/RECORD
